multi_thread/__init__.py
multi_thread/display_v2.py
multi_thread/queue_management.py
multi_thread/thread_pool_manager.py
multi_thread/thread_worker.py
multi_threader_kypkalorian-0.0.4.dist-info/METADATA
multi_threader_kypkalorian-0.0.4.dist-info/WHEEL
multi_threader_kypkalorian-0.0.4.dist-info/top_level.txt
multi_threader_kypkalorian-0.0.4.dist-info/RECORD
